tiger_notebook/__init__.py
tiger_notebook/_version.py
tiger_notebook/test.py
tiger_notebook/component_drill/__init__.py
tiger_notebook/component_drill/__main__.py
tiger_notebook/component_drill/drill/__init__.py
tiger_notebook/component_drill/drill/aistudio_argo_drill.py
tiger_notebook/component_drill/drill/base_drill.py
tiger_notebook/component_drill/drill/python_single_drill.py
tiger_notebook/component_drill/drill/sample_train_drill.py
tiger_notebook/component_drill/util/__init__.py
tiger_notebook/component_drill/util/log_util.py
tiger_notebook/jupyter_expression/__init__.py
tiger_notebook/public/__init__.py
tiger_notebook/public/tiger_executor.py
tiger_notebook-0.2.dist-info/METADATA
tiger_notebook-0.2.dist-info/WHEEL
tiger_notebook-0.2.dist-info/entry_points.txt
tiger_notebook-0.2.dist-info/top_level.txt
tiger_notebook-0.2.dist-info/RECORD
