Metadata-Version: 2.1
Name: tiger-notebook
Version: 0.2
Summary: tiger notebook
Home-page: UNKNOWN
Author: tiger
Author-email: UNKNOWN
License: UNKNOWN
Platform: UNKNOWN
